openapi_tools_mcp/__init__.py
openapi_tools_mcp/server.py
openapi_tools_mcp/tools.py
openapi_tools_mcp-0.1.0.dist-info/METADATA
openapi_tools_mcp-0.1.0.dist-info/WHEEL
openapi_tools_mcp-0.1.0.dist-info/entry_points.txt
openapi_tools_mcp-0.1.0.dist-info/licenses/LICENSE
openapi_tools_mcp-0.1.0.dist-info/RECORD
