Metadata-Version: 2.4
Name: openapi-tools-mcp
Version: 0.1.0
Summary: A Model Context Protocol server powered by fastMCP for inspecting local OpenAPI specs.
Project-URL: Homepage, https://github.com/kardaj/openapi-tools-mcp
Project-URL: Repository, https://github.com/kardaj/openapi-tools-mcp
Project-URL: Issues, https://github.com/kardaj/openapi-tools-mcp/issues
Author: kardaj
License: MIT License
License-File: LICENSE
Keywords: mcp,openapi,specs,tools
Classifier: License :: OSI Approved :: MIT License
Classifier: Operating System :: OS Independent
Classifier: Programming Language :: Python :: 3
Classifier: Programming Language :: Python :: 3 :: Only
Classifier: Programming Language :: Python :: 3.10
Classifier: Programming Language :: Python :: 3.11
Classifier: Programming Language :: Python :: 3.12
Requires-Python: >=3.10
Requires-Dist: fastmcp>=0.2.0
Requires-Dist: openapi-spec-validator>=0.7.1
Requires-Dist: pyyaml>=6.0
Provides-Extra: dev
Requires-Dist: black; extra == 'dev'
Requires-Dist: pytest; extra == 'dev'
Requires-Dist: pytest-black; extra == 'dev'
Requires-Dist: pytest-cov; extra == 'dev'
Requires-Dist: pytest-ruff; extra == 'dev'
Requires-Dist: ruff; extra == 'dev'
